graphwfc/GraphWFCState.py
graphwfc/__init__.py
graphwfc/__main__.py
graphwfc/helpers.py
GraphWFC-0.9.4.dist-info/LICENSE
GraphWFC-0.9.4.dist-info/METADATA
GraphWFC-0.9.4.dist-info/WHEEL
GraphWFC-0.9.4.dist-info/top_level.txt
GraphWFC-0.9.4.dist-info/RECORD
